kata2angka/__init__.py
kata2angka/konversi.py
kata2angka-0.1.2.dist-info/LICENSE
kata2angka-0.1.2.dist-info/LICENSE.txt
kata2angka-0.1.2.dist-info/METADATA
kata2angka-0.1.2.dist-info/WHEEL
kata2angka-0.1.2.dist-info/top_level.txt
kata2angka-0.1.2.dist-info/RECORD
