Metadata-Version: 2.1
Name: kata2angka
Version: 0.1.2
Summary: Konversi kata ke nomor.
Home-page: https://github.com/hermansh-id/kata2angka
Download-URL: https://github.com/hermansh-id/kata2angka/archive/refs/tags/beta0.1.tar.gz
Author: Herman Sugi Harto
Author-email: hermansh.id@gmail.com
License: MIT License
Keywords: numbers,convert,words,indonesia
Classifier: Intended Audience :: Developers
Classifier: Programming Language :: Python
License-File: LICENSE
License-File: LICENSE.txt
